bondpy/__init__.py
bondpy/bondapi.py
bondpy/devices/__init__.py
bondpy/devices/base.py
bondpy/devices/factory.py
bondpy/devices/fan.py
bondpy-0.1.10.dist-info/METADATA
bondpy-0.1.10.dist-info/RECORD
bondpy-0.1.10.dist-info/WHEEL
bondpy-0.1.10.dist-info/top_level.txt
